torchradiomics/TorchRadiomicsBase.py
torchradiomics/TorchRadiomicsFirstOrder.py
torchradiomics/TorchRadiomicsGLCM.py
torchradiomics/TorchRadiomicsGLDM.py
torchradiomics/TorchRadiomicsGLRLM.py
torchradiomics/TorchRadiomicsGLSZM.py
torchradiomics/TorchRadiomicsNGTDM.py
torchradiomics/__init__.py
pytorchradiomics-0.0.5.dist-info/LICENSE
pytorchradiomics-0.0.5.dist-info/METADATA
pytorchradiomics-0.0.5.dist-info/WHEEL
pytorchradiomics-0.0.5.dist-info/top_level.txt
pytorchradiomics-0.0.5.dist-info/RECORD
