Metadata-Version: 2.1
Name: pytorchradiomics
Version: 0.0.5
Summary: PyTorch implementation of PyRadiomics Extractor
Author-email: Wingkou <wingkou@outlook.com>
Project-URL: Homepage, https://github.com/lyhyl/pytorchradiomics#readme
Project-URL: Issues, https://github.com/lyhyl/pytorchradiomics/issues
Project-URL: Github, https://github.com/lyhyl/pytorchradiomics
Keywords: radiomics,cancerimaging,medicalresearch,computationalimaging
Classifier: Programming Language :: Python :: 3.10
Classifier: License :: OSI Approved :: MIT License
Classifier: Operating System :: OS Independent
Classifier: Topic :: Scientific/Engineering :: Bio-Informatics
Requires-Python: >=3.10
License-File: LICENSE
